aiutils/__init__.py
aiutils/csp.py
aiutils/games.py
aiutils/search.py
aiutils/utils.py
aistudent-1.0.3.dist-info/METADATA
aistudent-1.0.3.dist-info/WHEEL
aistudent-1.0.3.dist-info/top_level.txt
aistudent-1.0.3.dist-info/RECORD
