Metadata-Version: 2.2
Name: aistudent
Version: 1.0.3
Summary: A simple AI utilities package for search, CSP, and games.
Author: Babar Ahmad
Author-email: babar.ahmad@aumc.edu.pk
Classifier: Programming Language :: Python :: 3.12
Classifier: License :: OSI Approved :: MIT License
Classifier: Operating System :: OS Independent
Requires-Dist: numpy
Requires-Dist: matplotlib
Requires-Dist: networkx
Requires-Dist: sortedcontainers
Requires-Dist: pillow
Dynamic: author
Dynamic: author-email
Dynamic: classifier
Dynamic: description
Dynamic: description-content-type
Dynamic: requires-dist
Dynamic: summary
